spherical_coordinates/__init__.py
spherical_coordinates/base.py
spherical_coordinates/corsika.py
spherical_coordinates/dimensionality.py
spherical_coordinates/random.py
spherical_coordinates/version.py
spherical_coordinates-0.1.8.dist-info/licenses/LICENSE
spherical_coordinates-0.1.8.dist-info/METADATA
spherical_coordinates-0.1.8.dist-info/WHEEL
spherical_coordinates-0.1.8.dist-info/top_level.txt
spherical_coordinates-0.1.8.dist-info/RECORD
