Metadata-Version: 2.4
Name: spherical_coordinates
Version: 0.1.8
Summary: Transform spherical coordinates as it is done in KIT's CORSIKA.
Home-page: https://github.com/cherenkov-plenoscope/spherical_coordinates
Author: Sebastian A. Mueller
Author-email: sebastian-achim.mueller@mpi-hd.mpg.de
Classifier: Programming Language :: Python :: 3
Classifier: License :: OSI Approved :: MIT License
Classifier: Operating System :: OS Independent
Classifier: Natural Language :: English
License-File: LICENSE
Dynamic: author
Dynamic: author-email
Dynamic: classifier
Dynamic: description
Dynamic: description-content-type
Dynamic: home-page
Dynamic: license-file
Dynamic: summary
